<?xml version='1.0' encoding='UTF-8'?>
<commonRoad timeStepSize="0.1" commonRoadVersion="2020a" author="CONDI" affiliation="" source="" benchmarkID="ZAM_Test-1" date="2025-04-24">
  <location>
    <geoNameId>-999</geoNameId>
    <gpsLatitude>999</gpsLatitude>
    <gpsLongitude>999</gpsLongitude>
  </location>
  <scenarioTags/>
  <lanelet id="1">
    <leftBound>
      <point>
        <x>0.0052212196</x>
        <y>-0.0000181743</y>
      </point>
      <point>
        <x>2.0034849198</x>
        <y>-0.0069748512</y>
      </point>
      <point>
        <x>4.0099704642</x>
        <y>-0.0119713338</y>
      </point>
      <point>
        <x>6.0149576802</x>
        <y>-0.0169588499</y>
      </point>
      <point>
        <x>8.0199587766</x>
        <y>-0.0209551641</y>
      </point>
      <point>
        <x>10.0259489067</x>
        <y>-0.0249461779</y>
      </point>
      <point>
        <x>12.0309584405</x>
        <y>-0.0279507087</y>
      </point>
      <point>
        <x>14.0359697043</x>
        <y>-0.0299616705</y>
      </point>
      <point>
        <x>16.0409693190</x>
        <y>-0.0319561997</y>
      </point>
      <point>
        <x>18.0459827543</x>
        <y>-0.0329753706</y>
      </point>
      <point>
        <x>20.0510005950</x>
        <y>-0.0329999999</y>
      </point>
      <point>
        <x>22.0559828639</x>
        <y>-0.0339696583</y>
      </point>
      <point>
        <x>24.0610176253</x>
        <y>-0.0330330670</y>
      </point>
      <point>
        <x>26.0659999847</x>
        <y>-0.0329999999</y>
      </point>
      <point>
        <x>28.0720168099</x>
        <y>-0.0320380413</y>
      </point>
      <point>
        <x>30.0770295817</x>
        <y>-0.0300820193</y>
      </point>
      <point>
        <x>32.0820155495</x>
        <y>-0.0290437619</y>
      </point>
      <point>
        <x>34.0870287457</x>
        <y>-0.0270934572</y>
      </point>
      <point>
        <x>36.0920240275</x>
        <y>-0.0250984835</y>
      </point>
      <point>
        <x>38.0970238475</x>
        <y>-0.0231039289</y>
      </point>
      <point>
        <x>40.1020312719</x>
        <y>-0.0201647967</y>
      </point>
      <point>
        <x>42.1070172065</x>
        <y>-0.0181153753</y>
      </point>
      <point>
        <x>44.1120148061</x>
        <y>-0.0161208523</y>
      </point>
      <point>
        <x>46.1170213739</x>
        <y>-0.0131894700</y>
      </point>
      <point>
        <x>48.1230121690</x>
        <y>-0.0111312658</y>
      </point>
      <point>
        <x>50.1280081832</x>
        <y>-0.0091367719</y>
      </point>
      <point>
        <x>52.1330065238</x>
        <y>-0.0071427085</y>
      </point>
      <point>
        <x>54.1380056104</x>
        <y>-0.0051477556</y>
      </point>
      <point>
        <x>56.1430054353</x>
        <y>-0.0031531883</y>
      </point>
      <point>
        <x>58.1479999625</x>
        <y>-0.0011591248</y>
      </point>
      <point>
        <x>60.1530002899</x>
        <y>-0.0000823168</y>
      </point>
      <point>
        <x>62.1580009884</x>
        <y>0.0009147195</y>
      </point>
      <point>
        <x>64.1630015603</x>
        <y>0.0019121898</y>
      </point>
      <point>
        <x>66.1689987182</x>
        <y>0.0019999999</y>
      </point>
      <point>
        <x>68.1740032762</x>
        <y>0.0010930095</y>
      </point>
      <point>
        <x>70.1790005310</x>
        <y>0.0000957464</y>
      </point>
      <point>
        <x>72.1839981079</x>
        <y>0.0</y>
      </point>
      <point>
        <x>74.1890031921</x>
        <y>-0.0017975156</y>
      </point>
      <point>
        <x>76.1940002959</x>
        <y>-0.0028958231</y>
      </point>
      <point>
        <x>78.1989971796</x>
        <y>-0.0038930606</y>
      </point>
      <point>
        <x>80.2040019377</x>
        <y>-0.0048901053</y>
      </point>
      <point>
        <x>82.2090000609</x>
        <y>-0.0041126574</y>
      </point>
      <point>
        <x>84.2149958243</x>
        <y>-0.0022298002</y>
      </point>
      <point>
        <x>86.2200028605</x>
        <y>0.0006471114</y>
      </point>
      <point>
        <x>88.2242540650</x>
        <y>0.0049530376</y>
      </point>
      <point>
        <x>90.2300033435</x>
        <y>0.0090067197</y>
      </point>
      <point>
        <x>92.2357487621</x>
        <y>0.0125633984</y>
      </point>
      <point>
        <x>94.2399973778</x>
        <y>0.0147423473</y>
      </point>
      <point>
        <x>96.2450024409</x>
        <y>0.0141315572</y>
      </point>
      <point>
        <x>98.2499994243</x>
        <y>0.0088070628</y>
      </point>
      <point>
        <x>100.2542416088</x>
        <y>-0.0027768605</y>
      </point>
      <point>
        <x>102.2576972187</x>
        <y>-0.0392532534</y>
      </point>
      <point>
        <x>104.2561224570</x>
        <y>-0.1330777820</y>
      </point>
      <point>
        <x>106.2536870852</x>
        <y>-0.2839075556</y>
      </point>
      <point>
        <x>108.2841369695</x>
        <y>-0.4960108261</y>
      </point>
      <point>
        <x>110.2673200891</x>
        <y>-0.7615659870</y>
      </point>
      <point>
        <x>112.2420770424</x>
        <y>-1.0839586517</y>
      </point>
      <point>
        <x>114.2073604369</x>
        <y>-1.4627595531</y>
      </point>
      <point>
        <x>116.1617473230</x>
        <y>-1.8972376212</y>
      </point>
      <point>
        <x>118.1013481336</x>
        <y>-2.3871463242</y>
      </point>
      <point>
        <x>120.0256633489</x>
        <y>-2.9324787631</y>
      </point>
      <point>
        <x>121.9362891243</x>
        <y>-3.5325593050</y>
      </point>
      <point>
        <x>123.8270488279</x>
        <y>-4.1861969997</y>
      </point>
      <point>
        <x>125.6992200412</x>
        <y>-4.8945147057</y>
      </point>
      <point>
        <x>127.5503199029</x>
        <y>-5.6559533160</y>
      </point>
      <point>
        <x>129.3778556730</x>
        <y>-6.4694961146</y>
      </point>
      <point>
        <x>131.1831402969</x>
        <y>-7.3351355217</y>
      </point>
      <point>
        <x>132.9620374702</x>
        <y>-8.2511106321</y>
      </point>
      <point>
        <x>134.7142751682</x>
        <y>-9.2182831719</y>
      </point>
      <point>
        <x>136.4580950929</x>
        <y>-10.2477448179</y>
      </point>
      <point>
        <x>138.1686970810</x>
        <y>-11.3261986487</y>
      </point>
      <point>
        <x>139.8308036723</x>
        <y>-12.4417543712</y>
      </point>
      <point>
        <x>141.4597968514</x>
        <y>-13.6040900729</y>
      </point>
      <point>
        <x>143.0552355228</x>
        <y>-14.8124124081</y>
      </point>
      <point>
        <x>144.6153757210</x>
        <y>-16.0657984345</y>
      </point>
      <point>
        <x>146.1384793755</x>
        <y>-17.3633723495</y>
      </point>
      <point>
        <x>147.6241567915</x>
        <y>-18.7044473419</y>
      </point>
      <point>
        <x>149.0720472337</x>
        <y>-20.0873841092</y>
      </point>
      <point>
        <x>150.4791587070</x>
        <y>-21.5093675104</y>
      </point>
      <point>
        <x>151.8728227868</x>
        <y>-23.0032133936</y>
      </point>
      <point>
        <x>153.1934731063</x>
        <y>-24.5054785697</y>
      </point>
      <point>
        <x>154.4719879368</x>
        <y>-26.0453643603</y>
      </point>
      <point>
        <x>155.7062856848</x>
        <y>-27.6205390175</y>
      </point>
      <point>
        <x>156.8956948454</x>
        <y>-29.2313499500</y>
      </point>
      <point>
        <x>158.0369663673</x>
        <y>-30.8732436216</y>
      </point>
      <point>
        <x>159.1322184320</x>
        <y>-32.5489822957</y>
      </point>
      <point>
        <x>160.1788428224</x>
        <y>-34.2541480583</y>
      </point>
      <point>
        <x>161.1768078376</x>
        <y>-35.9901319900</y>
      </point>
      <point>
        <x>162.1242127033</x>
        <y>-37.7518931983</y>
      </point>
      <point>
        <x>163.0217142820</x>
        <y>-39.5416287018</y>
      </point>
      <point>
        <x>163.8668401541</x>
        <y>-41.3550673409</y>
      </point>
      <point>
        <x>164.6687999769</x>
        <y>-43.2133706855</y>
      </point>
      <point>
        <x>165.4152526003</x>
        <y>-45.0937777248</y>
      </point>
      <point>
        <x>166.1000882272</x>
        <y>-46.9746402722</y>
      </point>
      <point>
        <x>166.7309678048</x>
        <y>-48.8747275093</y>
      </point>
      <point>
        <x>167.3068665615</x>
        <y>-50.7902879671</y>
      </point>
      <point>
        <x>167.8286870441</x>
        <y>-52.7229949283</y>
      </point>
      <point>
        <x>168.2942621916</x>
        <y>-54.6685002939</y>
      </point>
      <point>
        <x>168.7048057554</x>
        <y>-56.6273684713</y>
      </point>
      <point>
        <x>169.0595084217</x>
        <y>-58.5972682823</y>
      </point>
      <point>
        <x>169.3572456560</x>
        <y>-60.5755416964</y>
      </point>
      <point>
        <x>169.5984891467</x>
        <y>-62.5633770548</y>
      </point>
      <point>
        <x>169.7829146737</x>
        <y>-64.5554618749</y>
      </point>
      <point>
        <x>169.9106762852</x>
        <y>-66.5525865710</y>
      </point>
      <point>
        <x>169.9820748110</x>
        <y>-68.5944885145</y>
      </point>
      <point>
        <x>169.9933999211</x>
        <y>-70.5956044282</y>
      </point>
      <point>
        <x>169.9471552833</x>
        <y>-72.5952773215</y>
      </point>
      <point>
        <x>169.8442431027</x>
        <y>-74.5948695475</y>
      </point>
      <point>
        <x>169.6844548824</x>
        <y>-76.5892742970</y>
      </point>
      <point>
        <x>169.4675623981</x>
        <y>-78.5790776047</y>
      </point>
      <point>
        <x>169.1946771120</x>
        <y>-80.5605113813</y>
      </point>
      <point>
        <x>168.8649131761</x>
        <y>-82.5354730130</y>
      </point>
      <point>
        <x>168.4783920485</x>
        <y>-84.4987854339</y>
      </point>
      <point>
        <x>168.0308736840</x>
        <y>-86.4715828704</y>
      </point>
      <point>
        <x>167.5260564509</x>
        <y>-88.4337969138</y>
      </point>
      <point>
        <x>166.9708080370</x>
        <y>-90.3549051120</y>
      </point>
      <point>
        <x>166.3607493824</x>
        <y>-92.2610074363</y>
      </point>
      <point>
        <x>165.6965471013</x>
        <y>-94.1496079032</y>
      </point>
      <point>
        <x>164.9790984612</x>
        <y>-96.0171645178</y>
      </point>
      <point>
        <x>164.2084253453</x>
        <y>-97.8646201797</y>
      </point>
      <point>
        <x>163.3855039514</x>
        <y>-99.6888366207</y>
      </point>
      <point>
        <x>162.5110516679</x>
        <y>-101.4882944246</y>
      </point>
      <point>
        <x>161.5851031083</x>
        <y>-103.2626355861</y>
      </point>
      <point>
        <x>160.6088517679</x>
        <y>-105.0103249204</y>
      </point>
      <point>
        <x>159.5835363822</x>
        <y>-106.7283788936</y>
      </point>
      <point>
        <x>158.5099610577</x>
        <y>-108.4167262274</y>
      </point>
      <point>
        <x>157.3874586495</x>
        <y>-110.0744570327</y>
      </point>
      <point>
        <x>156.2186140571</x>
        <y>-111.6989676737</y>
      </point>
      <point>
        <x>155.0044241377</x>
        <y>-113.2894496315</y>
      </point>
      <point>
        <x>153.7183057546</x>
        <y>-114.8761493531</y>
      </point>
      <point>
        <x>152.4134101695</x>
        <y>-116.3936465345</y>
      </point>
      <point>
        <x>151.0651744147</x>
        <y>-117.8737525421</y>
      </point>
      <point>
        <x>149.6763448276</x>
        <y>-119.3153521191</y>
      </point>
      <point>
        <x>148.2657900350</x>
        <y>-120.7407862817</y>
      </point>
      <point>
        <x>146.8522894669</x>
        <y>-122.1615405133</y>
      </point>
      <point>
        <x>145.4348055655</x>
        <y>-123.5808073078</y>
      </point>
      <point>
        <x>144.0158137322</x>
        <y>-124.9968085032</y>
      </point>
      <point>
        <x>142.5960632152</x>
        <y>-126.4130725338</y>
      </point>
      <point>
        <x>141.1751376863</x>
        <y>-127.8271386828</y>
      </point>
      <point>
        <x>139.7542017551</x>
        <y>-129.2422090656</y>
      </point>
      <point>
        <x>138.3335367734</x>
        <y>-130.6582874879</y>
      </point>
      <point>
        <x>136.9151920148</x>
        <y>-132.0751952920</y>
      </point>
      <point>
        <x>135.4971899575</x>
        <y>-133.4922004714</y>
      </point>
      <point>
        <x>134.0788525151</x>
        <y>-134.9098616262</y>
      </point>
      <point>
        <x>132.6622571683</x>
        <y>-136.3285039478</y>
      </point>
      <point>
        <x>131.2443010165</x>
        <y>-137.7487988392</y>
      </point>
      <point>
        <x>129.8284485929</x>
        <y>-139.1657004250</y>
      </point>
      <point>
        <x>128.4111895887</x>
        <y>-140.5844553924</y>
      </point>
      <point>
        <x>126.9936014193</x>
        <y>-142.0033503050</y>
      </point>
      <point>
        <x>125.5760969267</x>
        <y>-143.4203595424</y>
      </point>
      <point>
        <x>124.1576480696</x>
        <y>-144.8383945776</y>
      </point>
      <point>
        <x>122.7402080333</x>
        <y>-146.2562070215</y>
      </point>
      <point>
        <x>121.3221045983</x>
        <y>-147.6733557420</y>
      </point>
      <point>
        <x>119.9039979553</x>
        <y>-149.0910020446</y>
      </point>
      <point>
        <x>118.4852512514</x>
        <y>-150.5097462863</y>
      </point>
      <point>
        <x>117.0683546404</x>
        <y>-151.9266097441</y>
      </point>
      <point>
        <x>115.6502180039</x>
        <y>-153.3442107710</y>
      </point>
      <point>
        <x>114.2317544250</x>
        <y>-154.7617455749</y>
      </point>
      <point>
        <x>112.8141774862</x>
        <y>-156.1794217681</y>
      </point>
      <point>
        <x>111.3966402253</x>
        <y>-157.5983904634</y>
      </point>
      <point>
        <x>109.9792146631</x>
        <y>-159.0162250096</y>
      </point>
      <point>
        <x>108.5603866450</x>
        <y>-160.4341415823</y>
      </point>
      <point>
        <x>107.1434106070</x>
        <y>-161.8516723045</y>
      </point>
      <point>
        <x>105.7265811411</x>
        <y>-163.2698421008</y>
      </point>
      <point>
        <x>104.3079767563</x>
        <y>-164.6869740189</y>
      </point>
      <point>
        <x>102.8891400248</x>
        <y>-166.1048827484</y>
      </point>
      <point>
        <x>101.4717525634</x>
        <y>-167.5227474365</y>
      </point>
      <point>
        <x>100.0537532958</x>
        <y>-168.9407467041</y>
      </point>
      <point>
        <x>98.6357540283</x>
        <y>-170.3587459716</y>
      </point>
      <point>
        <x>97.2187503967</x>
        <y>-171.7757496032</y>
      </point>
      <point>
        <x>95.8011324636</x>
        <y>-173.1933841570</y>
      </point>
      <point>
        <x>94.3826361840</x>
        <y>-174.6123786749</y>
      </point>
      <point>
        <x>92.9656152505</x>
        <y>-176.0298716452</y>
      </point>
      <point>
        <x>91.5469995117</x>
        <y>-177.4480004882</y>
      </point>
      <point>
        <x>90.1286212893</x>
        <y>-178.8663670166</y>
      </point>
      <point>
        <x>88.7117466125</x>
        <y>-180.2827533874</y>
      </point>
      <point>
        <x>87.2937554383</x>
        <y>-181.7007609195</y>
      </point>
      <point>
        <x>85.8766178895</x>
        <y>-183.1188756891</y>
      </point>
      <point>
        <x>84.4579988098</x>
        <y>-184.5370011901</y>
      </point>
      <point>
        <x>83.0399995422</x>
        <y>-185.9550004577</y>
      </point>
      <point>
        <x>81.6216255399</x>
        <y>-187.3733712078</y>
      </point>
      <point>
        <x>80.2043819097</x>
        <y>-188.7901195822</y>
      </point>
      <point>
        <x>78.7870025024</x>
        <y>-190.2079974975</y>
      </point>
      <lineMarking>no_marking</lineMarking>
    </leftBound>
    <rightBound>
      <point>
        <x>0.0</x>
        <y>-3.0</y>
      </point>
      <point>
        <x>1.9945281627</x>
        <y>-3.0069461179</y>
      </point>
      <point>
        <x>4.0025115316</x>
        <y>-3.0119540316</y>
      </point>
      <point>
        <x>6.0074950368</x>
        <y>-3.0169415299</y>
      </point>
      <point>
        <x>8.0139916178</x>
        <y>-3.0209442896</y>
      </point>
      <point>
        <x>10.0199802491</x>
        <y>-3.0249362791</y>
      </point>
      <point>
        <x>12.0264830629</x>
        <y>-3.0279455242</y>
      </point>
      <point>
        <x>14.0329853660</x>
        <y>-3.0299601844</y>
      </point>
      <point>
        <x>16.0379849965</x>
        <y>-3.0319542366</y>
      </point>
      <point>
        <x>18.0444905840</x>
        <y>-3.0329753684</y>
      </point>
      <point>
        <x>20.0510005950</x>
        <y>-3.033</y>
      </point>
      <point>
        <x>22.0544910686</x>
        <y>-3.0339699110</y>
      </point>
      <point>
        <x>24.0625097946</x>
        <y>-3.0330310896</y>
      </point>
      <point>
        <x>26.0659999847</x>
        <y>-3.033</y>
      </point>
      <point>
        <x>28.0735089791</x>
        <y>-3.0320360651</y>
      </point>
      <point>
        <x>30.0800131666</x>
        <y>-3.0300765657</y>
      </point>
      <point>
        <x>32.0835077182</x>
        <y>-3.0290415384</y>
      </point>
      <point>
        <x>34.0900123301</x>
        <y>-3.0270875063</y>
      </point>
      <point>
        <x>36.0950090962</x>
        <y>-3.0250925282</y>
      </point>
      <point>
        <x>38.1000081792</x>
        <y>-3.0230975042</y>
      </point>
      <point>
        <x>40.1065066395</x>
        <y>-3.0201528990</y>
      </point>
      <point>
        <x>42.1100015365</x>
        <y>-3.0181084561</y>
      </point>
      <point>
        <x>44.1149991281</x>
        <y>-3.0161143718</y>
      </point>
      <point>
        <x>46.1214978587</x>
        <y>-3.0131768688</y>
      </point>
      <point>
        <x>48.1259957523</x>
        <y>-3.0111243204</y>
      </point>
      <point>
        <x>50.1309925106</x>
        <y>-3.0091293606</y>
      </point>
      <point>
        <x>52.1359901066</x>
        <y>-3.0071352659</y>
      </point>
      <point>
        <x>54.1409906776</x>
        <y>-3.0051403077</y>
      </point>
      <point>
        <x>56.1459897606</x>
        <y>-3.0031452838</y>
      </point>
      <point>
        <x>58.1509835449</x>
        <y>-3.0011511849</y>
      </point>
      <point>
        <x>60.1544924544</x>
        <y>-3.0000788594</y>
      </point>
      <point>
        <x>62.1594927818</x>
        <y>-2.9990818036</y>
      </point>
      <point>
        <x>64.1644940959</x>
        <y>-2.9980843312</y>
      </point>
      <point>
        <x>66.1689987182</x>
        <y>-2.998</y>
      </point>
      <point>
        <x>68.1725111089</x>
        <y>-2.9989092095</y>
      </point>
      <point>
        <x>70.1775083635</x>
        <y>-2.9999067205</y>
      </point>
      <point>
        <x>72.1839981079</x>
        <y>-3.0</y>
      </point>
      <point>
        <x>74.1860181140</x>
        <y>-3.0018010130</y>
      </point>
      <point>
        <x>76.1925084995</x>
        <y>-3.0028983135</y>
      </point>
      <point>
        <x>78.1975050120</x>
        <y>-3.0038957736</y>
      </point>
      <point>
        <x>80.2025101412</x>
        <y>-3.0048928444</y>
      </point>
      <point>
        <x>82.2104922249</x>
        <y>-3.0041082128</y>
      </point>
      <point>
        <x>84.2179801467</x>
        <y>-3.0022198108</y>
      </point>
      <point>
        <x>86.2244793328</x>
        <y>-2.9993351054</y>
      </point>
      <point>
        <x>88.2309695264</x>
        <y>-2.9954537919</y>
      </point>
      <point>
        <x>90.2359714633</x>
        <y>-2.9914654968</y>
      </point>
      <point>
        <x>92.2409717062</x>
        <y>-2.9874756781</y>
      </point>
      <point>
        <x>94.2429816993</x>
        <y>-2.9852466616</y>
      </point>
      <point>
        <x>96.2435102730</x>
        <y>-2.9858718956</y>
      </point>
      <point>
        <x>98.2410486576</x>
        <y>-2.9911915922</y>
      </point>
      <point>
        <x>100.2355868462</x>
        <y>-3.0031475766</y>
      </point>
      <point>
        <x>102.1972318856</x>
        <y>-3.0400048453</y>
      </point>
      <point>
        <x>104.1015695812</x>
        <y>-3.1314190810</y>
      </point>
      <point>
        <x>106.0146870542</x>
        <y>-3.2772157019</y>
      </point>
      <point>
        <x>107.9190613253</x>
        <y>-3.4766505803</y>
      </point>
      <point>
        <x>109.8162567945</x>
        <y>-3.7302781121</y>
      </point>
      <point>
        <x>111.7051901761</x>
        <y>-4.0381867681</y>
      </point>
      <point>
        <x>113.5863368376</x>
        <y>-4.4000717864</y>
      </point>
      <point>
        <x>115.4571441139</x>
        <y>-4.8150606977</y>
      </point>
      <point>
        <x>117.3116133044</x>
        <y>-5.2826634509</y>
      </point>
      <point>
        <x>119.1540040404</x>
        <y>-5.8042121285</y>
      </point>
      <point>
        <x>120.9832598329</x>
        <y>-6.3782289006</y>
      </point>
      <point>
        <x>122.7913628172</x>
        <y>-7.0022349724</y>
      </point>
      <point>
        <x>124.5832444884</x>
        <y>-7.6792040808</y>
      </point>
      <point>
        <x>126.3544549958</x>
        <y>-8.4064704952</y>
      </point>
      <point>
        <x>128.1042654297</x>
        <y>-9.1843972484</y>
      </point>
      <point>
        <x>129.8329364634</x>
        <y>-10.0123585832</y>
      </point>
      <point>
        <x>131.5347234817</x>
        <y>-10.8871800419</y>
      </point>
      <point>
        <x>133.2118506508</x>
        <y>-11.8116947835</y>
      </point>
      <point>
        <x>134.902</x>
        <y>-12.809</y>
      </point>
      <point>
        <x>136.5572324233</x>
        <y>-13.8537437589</y>
      </point>
      <point>
        <x>138.1474789134</x>
        <y>-14.9231354648</y>
      </point>
      <point>
        <x>139.7047948356</x>
        <y>-16.0363455861</y>
      </point>
      <point>
        <x>141.2309516978</x>
        <y>-17.1940613794</y>
      </point>
      <point>
        <x>142.7225628477</x>
        <y>-18.3943213164</y>
      </point>
      <point>
        <x>144.1782801335</x>
        <y>-19.6363245892</y>
      </point>
      <point>
        <x>145.5984762581</x>
        <y>-20.9205048562</y>
      </point>
      <point>
        <x>146.9845566744</x>
        <y>-22.2457750098</y>
      </point>
      <point>
        <x>148.3302757629</x>
        <y>-23.6074328942</y>
      </point>
      <point>
        <x>149.6351012767</x>
        <y>-25.0064487424</y>
      </point>
      <point>
        <x>150.8995288171</x>
        <y>-26.4432787385</y>
      </point>
      <point>
        <x>152.1243898738</x>
        <y>-27.9173509456</y>
      </point>
      <point>
        <x>153.3058613681</x>
        <y>-29.4236815937</y>
      </point>
      <point>
        <x>154.4447652281</x>
        <y>-30.9643332266</y>
      </point>
      <point>
        <x>155.5374843057</x>
        <y>-32.5343449224</y>
      </point>
      <point>
        <x>156.5867094044</x>
        <y>-34.1380603229</y>
      </point>
      <point>
        <x>157.5888225624</x>
        <y>-35.7681549317</y>
      </point>
      <point>
        <x>158.5449718129</x>
        <y>-37.4291210643</y>
      </point>
      <point>
        <x>159.4529887965</x>
        <y>-39.1146944760</y>
      </point>
      <point>
        <x>160.3124771221</x>
        <y>-40.8253965251</y>
      </point>
      <point>
        <x>161.1229281438</x>
        <y>-42.5611322777</y>
      </point>
      <point>
        <x>161.9</x>
        <y>-44.36</y>
      </point>
      <point>
        <x>162.6220248493</x>
        <y>-46.1811395998</y>
      </point>
      <point>
        <x>163.2763543992</x>
        <y>-47.9820216272</y>
      </point>
      <point>
        <x>163.8787499527</x>
        <y>-49.8001344104</y>
      </point>
      <point>
        <x>164.4284785437</x>
        <y>-51.6339028638</y>
      </point>
      <point>
        <x>164.9269260627</x>
        <y>-53.4838777113</y>
      </point>
      <point>
        <x>165.3710006270</x>
        <y>-55.3446495096</y>
      </point>
      <point>
        <x>165.7627248353</x>
        <y>-57.2205528487</y>
      </point>
      <point>
        <x>166.1010824946</x>
        <y>-59.1056294774</y>
      </point>
      <point>
        <x>166.3846072719</x>
        <y>-60.9975166485</y>
      </point>
      <point>
        <x>166.6144424480</x>
        <y>-62.9001409891</y>
      </point>
      <point>
        <x>166.7900647169</x>
        <y>-64.8063317788</y>
      </point>
      <point>
        <x>166.9114887404</x>
        <y>-66.7176394876</y>
      </point>
      <point>
        <x>166.9786125334</x>
        <y>-68.6318664502</y>
      </point>
      <point>
        <x>166.9910497476</x>
        <y>-70.5456002906</y>
      </point>
      <point>
        <x>166.9483131303</x>
        <y>-72.4594176884</y>
      </point>
      <point>
        <x>166.8508032241</x>
        <y>-74.3731692102</y>
      </point>
      <point>
        <x>166.6995978389</x>
        <y>-76.2810889424</y>
      </point>
      <point>
        <x>166.4933314871</x>
        <y>-78.1859409289</y>
      </point>
      <point>
        <x>166.2337787579</x>
        <y>-80.0824305974</y>
      </point>
      <point>
        <x>165.9199163443</x>
        <y>-81.9709196169</y>
      </point>
      <point>
        <x>165.5516340169</x>
        <y>-83.8501997586</y>
      </point>
      <point>
        <x>165.119</x>
        <y>-85.761</y>
      </point>
      <point>
        <x>164.6295486643</x>
        <y>-87.6631192625</y>
      </point>
      <point>
        <x>164.0974540422</x>
        <y>-89.4988265571</y>
      </point>
      <point>
        <x>163.5124790818</x>
        <y>-91.3235477612</y>
      </point>
      <point>
        <x>162.8760992376</x>
        <y>-93.1304578429</y>
      </point>
      <point>
        <x>162.1887202072</x>
        <y>-94.9169932401</y>
      </point>
      <point>
        <x>161.4502439202</x>
        <y>-96.6847941441</y>
      </point>
      <point>
        <x>160.6620619026</x>
        <y>-98.4296867922</y>
      </point>
      <point>
        <x>159.8245941628</x>
        <y>-100.1510302129</y>
      </point>
      <point>
        <x>158.9379584861</x>
        <y>-101.8479732082</y>
      </point>
      <point>
        <x>158.0028708438</x>
        <y>-103.5207448844</y>
      </point>
      <point>
        <x>157.0221914304</x>
        <y>-105.1636222393</y>
      </point>
      <point>
        <x>155.9936060404</x>
        <y>-106.7796758210</y>
      </point>
      <point>
        <x>154.9200898645</x>
        <y>-108.3642805041</y>
      </point>
      <point>
        <x>153.8005381721</x>
        <y>-109.9191481683</y>
      </point>
      <point>
        <x>152.6381868836</x>
        <y>-111.4406217334</y>
      </point>
      <point>
        <x>151.4328155454</x>
        <y>-112.9282694020</y>
      </point>
      <point>
        <x>150.1850316137</x>
        <y>-114.3817713820</y>
      </point>
      <point>
        <x>148.8993710318</x>
        <y>-115.7960498286</y>
      </point>
      <point>
        <x>147.5431930875</x>
        <y>-117.2060678110</y>
      </point>
      <point>
        <x>146.1385703843</x>
        <y>-118.6255047299</y>
      </point>
      <point>
        <x>144.7291380811</x>
        <y>-120.0421192896</y>
      </point>
      <point>
        <x>143.3155520476</x>
        <y>-121.4570780690</y>
      </point>
      <point>
        <x>141.8965605459</x>
        <y>-122.8730780215</y>
      </point>
      <point>
        <x>140.4798130849</x>
        <y>-124.2863754705</y>
      </point>
      <point>
        <x>139.0581344261</x>
        <y>-125.7011840346</y>
      </point>
      <point>
        <x>137.6364490552</x>
        <y>-127.1169942349</y>
      </point>
      <point>
        <x>136.2131881862</x>
        <y>-128.5357008350</y>
      </point>
      <point>
        <x>134.7946899711</x>
        <y>-129.9532015126</y>
      </point>
      <point>
        <x>133.3766880209</x>
        <y>-131.3702062744</y>
      </point>
      <point>
        <x>131.9561084852</x>
        <y>-132.7901010735</y>
      </point>
      <point>
        <x>130.5391130493</x>
        <y>-134.2090910167</y>
      </point>
      <point>
        <x>129.1221050237</x>
        <y>-135.6280946876</y>
      </point>
      <point>
        <x>127.7063033539</x>
        <y>-137.0457928435</y>
      </point>
      <point>
        <x>126.2887950522</x>
        <y>-138.4642986880</y>
      </point>
      <point>
        <x>124.8724986572</x>
        <y>-139.8815013427</y>
      </point>
      <point>
        <x>123.4551982784</x>
        <y>-141.2987146598</y>
      </point>
      <point>
        <x>122.0357962919</x>
        <y>-142.7172890027</y>
      </point>
      <point>
        <x>120.6197057450</x>
        <y>-144.1342124727</y>
      </point>
      <point>
        <x>119.2012078843</x>
        <y>-145.5517127962</y>
      </point>
      <point>
        <x>117.7824979553</x>
        <y>-146.9695020446</y>
      </point>
      <point>
        <x>116.3637898532</x>
        <y>-148.3882848899</y>
      </point>
      <point>
        <x>114.9477098607</x>
        <y>-149.8052189085</y>
      </point>
      <point>
        <x>113.5297155398</x>
        <y>-151.2222160462</y>
      </point>
      <point>
        <x>112.1105044250</x>
        <y>-152.6404955749</y>
      </point>
      <point>
        <x>110.6917910439</x>
        <y>-154.0592731424</y>
      </point>
      <point>
        <x>109.2747824648</x>
        <y>-155.4772789127</y>
      </point>
      <point>
        <x>107.8587120232</x>
        <y>-156.8942301089</y>
      </point>
      <point>
        <x>106.4387776540</x>
        <y>-158.3132788007</y>
      </point>
      <point>
        <x>105.0212773305</x>
        <y>-159.7317766615</y>
      </point>
      <point>
        <x>103.6064388367</x>
        <y>-161.1474619908</y>
      </point>
      <point>
        <x>102.1872238451</x>
        <y>-162.5647291955</y>
      </point>
      <point>
        <x>100.7672782185</x>
        <y>-163.9837673280</y>
      </point>
      <point>
        <x>99.3505025634</x>
        <y>-165.4014974365</y>
      </point>
      <point>
        <x>97.9325032958</x>
        <y>-166.8194967041</y>
      </point>
      <point>
        <x>96.5145040283</x>
        <y>-168.2374959716</y>
      </point>
      <point>
        <x>95.0975003967</x>
        <y>-169.6544996032</y>
      </point>
      <point>
        <x>93.6795011291</x>
        <y>-171.0724988708</y>
      </point>
      <point>
        <x>92.2607705066</x>
        <y>-172.4912592115</y>
      </point>
      <point>
        <x>90.8447317217</x>
        <y>-173.9082420698</y>
      </point>
      <point>
        <x>89.4254995117</x>
        <y>-175.3265004882</y>
      </point>
      <point>
        <x>88.0075002441</x>
        <y>-176.7444997558</y>
      </point>
      <point>
        <x>86.5904966125</x>
        <y>-178.1615033874</y>
      </point>
      <point>
        <x>85.1717593061</x>
        <y>-179.5802570490</y>
      </point>
      <point>
        <x>83.7557377017</x>
        <y>-180.9972494556</y>
      </point>
      <point>
        <x>82.3364988098</x>
        <y>-182.4155011901</y>
      </point>
      <point>
        <x>80.9184995422</x>
        <y>-183.8335004577</y>
      </point>
      <point>
        <x>79.5005002746</x>
        <y>-185.2514997253</y>
      </point>
      <point>
        <x>78.0827595471</x>
        <y>-186.6692434370</y>
      </point>
      <point>
        <x>76.666</x>
        <y>-188.087</y>
      </point>
      <lineMarking>no_marking</lineMarking>
    </rightBound>
    <adjacentLeft ref="2" drivingDir="opposite"/>
    <laneletType>highway</laneletType>
  </lanelet>
  <lanelet id="2">
    <leftBound>
      <point>
        <x>78.7870025024</x>
        <y>-190.2079974975</y>
      </point>
      <point>
        <x>80.2043819097</x>
        <y>-188.7901195822</y>
      </point>
      <point>
        <x>81.6216255399</x>
        <y>-187.3733712078</y>
      </point>
      <point>
        <x>83.0399995422</x>
        <y>-185.9550004577</y>
      </point>
      <point>
        <x>84.4579988098</x>
        <y>-184.5370011901</y>
      </point>
      <point>
        <x>85.8766178895</x>
        <y>-183.1188756891</y>
      </point>
      <point>
        <x>87.2937554383</x>
        <y>-181.7007609195</y>
      </point>
      <point>
        <x>88.7117466125</x>
        <y>-180.2827533874</y>
      </point>
      <point>
        <x>90.1286212893</x>
        <y>-178.8663670166</y>
      </point>
      <point>
        <x>91.5469995117</x>
        <y>-177.4480004882</y>
      </point>
      <point>
        <x>92.9656152505</x>
        <y>-176.0298716452</y>
      </point>
      <point>
        <x>94.3826361840</x>
        <y>-174.6123786749</y>
      </point>
      <point>
        <x>95.8011324636</x>
        <y>-173.1933841570</y>
      </point>
      <point>
        <x>97.2187503967</x>
        <y>-171.7757496032</y>
      </point>
      <point>
        <x>98.6357540283</x>
        <y>-170.3587459716</y>
      </point>
      <point>
        <x>100.0537532958</x>
        <y>-168.9407467041</y>
      </point>
      <point>
        <x>101.4717525634</x>
        <y>-167.5227474365</y>
      </point>
      <point>
        <x>102.8891400248</x>
        <y>-166.1048827484</y>
      </point>
      <point>
        <x>104.3079767563</x>
        <y>-164.6869740189</y>
      </point>
      <point>
        <x>105.7265811411</x>
        <y>-163.2698421008</y>
      </point>
      <point>
        <x>107.1434106070</x>
        <y>-161.8516723045</y>
      </point>
      <point>
        <x>108.5603866450</x>
        <y>-160.4341415823</y>
      </point>
      <point>
        <x>109.9792146631</x>
        <y>-159.0162250096</y>
      </point>
      <point>
        <x>111.3966402253</x>
        <y>-157.5983904634</y>
      </point>
      <point>
        <x>112.8141774862</x>
        <y>-156.1794217681</y>
      </point>
      <point>
        <x>114.2317544250</x>
        <y>-154.7617455749</y>
      </point>
      <point>
        <x>115.6502180039</x>
        <y>-153.3442107710</y>
      </point>
      <point>
        <x>117.0683546404</x>
        <y>-151.9266097441</y>
      </point>
      <point>
        <x>118.4852512514</x>
        <y>-150.5097462863</y>
      </point>
      <point>
        <x>119.9039979553</x>
        <y>-149.0910020446</y>
      </point>
      <point>
        <x>121.3221045983</x>
        <y>-147.6733557420</y>
      </point>
      <point>
        <x>122.7402080333</x>
        <y>-146.2562070215</y>
      </point>
      <point>
        <x>124.1576480696</x>
        <y>-144.8383945776</y>
      </point>
      <point>
        <x>125.5760969267</x>
        <y>-143.4203595424</y>
      </point>
      <point>
        <x>126.9936014193</x>
        <y>-142.0033503050</y>
      </point>
      <point>
        <x>128.4111895887</x>
        <y>-140.5844553924</y>
      </point>
      <point>
        <x>129.8284485929</x>
        <y>-139.1657004250</y>
      </point>
      <point>
        <x>131.2443010165</x>
        <y>-137.7487988392</y>
      </point>
      <point>
        <x>132.6622571683</x>
        <y>-136.3285039478</y>
      </point>
      <point>
        <x>134.0788525151</x>
        <y>-134.9098616262</y>
      </point>
      <point>
        <x>135.4971899575</x>
        <y>-133.4922004714</y>
      </point>
      <point>
        <x>136.9151920148</x>
        <y>-132.0751952920</y>
      </point>
      <point>
        <x>138.3335367734</x>
        <y>-130.6582874879</y>
      </point>
      <point>
        <x>139.7542017551</x>
        <y>-129.2422090656</y>
      </point>
      <point>
        <x>141.1751376863</x>
        <y>-127.8271386828</y>
      </point>
      <point>
        <x>142.5960632152</x>
        <y>-126.4130725338</y>
      </point>
      <point>
        <x>144.0158137322</x>
        <y>-124.9968085032</y>
      </point>
      <point>
        <x>145.4348055655</x>
        <y>-123.5808073078</y>
      </point>
      <point>
        <x>146.8522894669</x>
        <y>-122.1615405133</y>
      </point>
      <point>
        <x>148.2657900350</x>
        <y>-120.7407862817</y>
      </point>
      <point>
        <x>149.6763448276</x>
        <y>-119.3153521191</y>
      </point>
      <point>
        <x>151.0651744147</x>
        <y>-117.8737525421</y>
      </point>
      <point>
        <x>152.4134101695</x>
        <y>-116.3936465345</y>
      </point>
      <point>
        <x>153.7183057546</x>
        <y>-114.8761493531</y>
      </point>
      <point>
        <x>155.0044241377</x>
        <y>-113.2894496315</y>
      </point>
      <point>
        <x>156.2186140571</x>
        <y>-111.6989676737</y>
      </point>
      <point>
        <x>157.3874586495</x>
        <y>-110.0744570327</y>
      </point>
      <point>
        <x>158.5099610577</x>
        <y>-108.4167262274</y>
      </point>
      <point>
        <x>159.5835363822</x>
        <y>-106.7283788936</y>
      </point>
      <point>
        <x>160.6088517679</x>
        <y>-105.0103249204</y>
      </point>
      <point>
        <x>161.5851031083</x>
        <y>-103.2626355861</y>
      </point>
      <point>
        <x>162.5110516679</x>
        <y>-101.4882944246</y>
      </point>
      <point>
        <x>163.3855039514</x>
        <y>-99.6888366207</y>
      </point>
      <point>
        <x>164.2084253453</x>
        <y>-97.8646201797</y>
      </point>
      <point>
        <x>164.9790984612</x>
        <y>-96.0171645178</y>
      </point>
      <point>
        <x>165.6965471013</x>
        <y>-94.1496079032</y>
      </point>
      <point>
        <x>166.3607493824</x>
        <y>-92.2610074363</y>
      </point>
      <point>
        <x>166.9708080370</x>
        <y>-90.3549051120</y>
      </point>
      <point>
        <x>167.5260564509</x>
        <y>-88.4337969138</y>
      </point>
      <point>
        <x>168.0308736840</x>
        <y>-86.4715828704</y>
      </point>
      <point>
        <x>168.4783920485</x>
        <y>-84.4987854339</y>
      </point>
      <point>
        <x>168.8649131761</x>
        <y>-82.5354730130</y>
      </point>
      <point>
        <x>169.1946771120</x>
        <y>-80.5605113813</y>
      </point>
      <point>
        <x>169.4675623981</x>
        <y>-78.5790776047</y>
      </point>
      <point>
        <x>169.6844548824</x>
        <y>-76.5892742970</y>
      </point>
      <point>
        <x>169.8442431027</x>
        <y>-74.5948695475</y>
      </point>
      <point>
        <x>169.9471552833</x>
        <y>-72.5952773215</y>
      </point>
      <point>
        <x>169.9933999211</x>
        <y>-70.5956044282</y>
      </point>
      <point>
        <x>169.9820748110</x>
        <y>-68.5944885145</y>
      </point>
      <point>
        <x>169.9106762852</x>
        <y>-66.5525865710</y>
      </point>
      <point>
        <x>169.7829146737</x>
        <y>-64.5554618749</y>
      </point>
      <point>
        <x>169.5984891467</x>
        <y>-62.5633770548</y>
      </point>
      <point>
        <x>169.3572456560</x>
        <y>-60.5755416964</y>
      </point>
      <point>
        <x>169.0595084217</x>
        <y>-58.5972682823</y>
      </point>
      <point>
        <x>168.7048057554</x>
        <y>-56.6273684713</y>
      </point>
      <point>
        <x>168.2942621916</x>
        <y>-54.6685002939</y>
      </point>
      <point>
        <x>167.8286870441</x>
        <y>-52.7229949283</y>
      </point>
      <point>
        <x>167.3068665615</x>
        <y>-50.7902879671</y>
      </point>
      <point>
        <x>166.7309678048</x>
        <y>-48.8747275093</y>
      </point>
      <point>
        <x>166.1000882272</x>
        <y>-46.9746402722</y>
      </point>
      <point>
        <x>165.4152526003</x>
        <y>-45.0937777248</y>
      </point>
      <point>
        <x>164.6687999769</x>
        <y>-43.2133706855</y>
      </point>
      <point>
        <x>163.8668401541</x>
        <y>-41.3550673409</y>
      </point>
      <point>
        <x>163.0217142820</x>
        <y>-39.5416287018</y>
      </point>
      <point>
        <x>162.1242127033</x>
        <y>-37.7518931983</y>
      </point>
      <point>
        <x>161.1768078376</x>
        <y>-35.9901319900</y>
      </point>
      <point>
        <x>160.1788428224</x>
        <y>-34.2541480583</y>
      </point>
      <point>
        <x>159.1322184320</x>
        <y>-32.5489822957</y>
      </point>
      <point>
        <x>158.0369663673</x>
        <y>-30.8732436216</y>
      </point>
      <point>
        <x>156.8956948454</x>
        <y>-29.2313499500</y>
      </point>
      <point>
        <x>155.7062856848</x>
        <y>-27.6205390175</y>
      </point>
      <point>
        <x>154.4719879368</x>
        <y>-26.0453643603</y>
      </point>
      <point>
        <x>153.1934731063</x>
        <y>-24.5054785697</y>
      </point>
      <point>
        <x>151.8728227868</x>
        <y>-23.0032133936</y>
      </point>
      <point>
        <x>150.4791587070</x>
        <y>-21.5093675104</y>
      </point>
      <point>
        <x>149.0720472337</x>
        <y>-20.0873841092</y>
      </point>
      <point>
        <x>147.6241567915</x>
        <y>-18.7044473419</y>
      </point>
      <point>
        <x>146.1384793755</x>
        <y>-17.3633723495</y>
      </point>
      <point>
        <x>144.6153757210</x>
        <y>-16.0657984345</y>
      </point>
      <point>
        <x>143.0552355228</x>
        <y>-14.8124124081</y>
      </point>
      <point>
        <x>141.4597968514</x>
        <y>-13.6040900729</y>
      </point>
      <point>
        <x>139.8308036723</x>
        <y>-12.4417543712</y>
      </point>
      <point>
        <x>138.1686970810</x>
        <y>-11.3261986487</y>
      </point>
      <point>
        <x>136.4580950929</x>
        <y>-10.2477448179</y>
      </point>
      <point>
        <x>134.7142751682</x>
        <y>-9.2182831719</y>
      </point>
      <point>
        <x>132.9620374702</x>
        <y>-8.2511106321</y>
      </point>
      <point>
        <x>131.1831402969</x>
        <y>-7.3351355217</y>
      </point>
      <point>
        <x>129.3778556730</x>
        <y>-6.4694961146</y>
      </point>
      <point>
        <x>127.5503199029</x>
        <y>-5.6559533160</y>
      </point>
      <point>
        <x>125.6992200412</x>
        <y>-4.8945147057</y>
      </point>
      <point>
        <x>123.8270488279</x>
        <y>-4.1861969997</y>
      </point>
      <point>
        <x>121.9362891243</x>
        <y>-3.5325593050</y>
      </point>
      <point>
        <x>120.0256633489</x>
        <y>-2.9324787631</y>
      </point>
      <point>
        <x>118.1013481336</x>
        <y>-2.3871463242</y>
      </point>
      <point>
        <x>116.1617473230</x>
        <y>-1.8972376212</y>
      </point>
      <point>
        <x>114.2073604369</x>
        <y>-1.4627595531</y>
      </point>
      <point>
        <x>112.2420770424</x>
        <y>-1.0839586517</y>
      </point>
      <point>
        <x>110.2673200891</x>
        <y>-0.7615659870</y>
      </point>
      <point>
        <x>108.2841369695</x>
        <y>-0.4960108261</y>
      </point>
      <point>
        <x>106.2536870852</x>
        <y>-0.2839075556</y>
      </point>
      <point>
        <x>104.2561224570</x>
        <y>-0.1330777820</y>
      </point>
      <point>
        <x>102.2576972187</x>
        <y>-0.0392532534</y>
      </point>
      <point>
        <x>100.2542416088</x>
        <y>-0.0027768605</y>
      </point>
      <point>
        <x>98.2499994243</x>
        <y>0.0088070628</y>
      </point>
      <point>
        <x>96.2450024409</x>
        <y>0.0141315572</y>
      </point>
      <point>
        <x>94.2399973778</x>
        <y>0.0147423473</y>
      </point>
      <point>
        <x>92.2357487621</x>
        <y>0.0125633984</y>
      </point>
      <point>
        <x>90.2300033435</x>
        <y>0.0090067197</y>
      </point>
      <point>
        <x>88.2242540650</x>
        <y>0.0049530376</y>
      </point>
      <point>
        <x>86.2200028605</x>
        <y>0.0006471114</y>
      </point>
      <point>
        <x>84.2149958243</x>
        <y>-0.0022298002</y>
      </point>
      <point>
        <x>82.2090000609</x>
        <y>-0.0041126574</y>
      </point>
      <point>
        <x>80.2040019377</x>
        <y>-0.0048901053</y>
      </point>
      <point>
        <x>78.1989971796</x>
        <y>-0.0038930606</y>
      </point>
      <point>
        <x>76.1940002959</x>
        <y>-0.0028958231</y>
      </point>
      <point>
        <x>74.1890031921</x>
        <y>-0.0017975156</y>
      </point>
      <point>
        <x>72.1839981079</x>
        <y>0.0</y>
      </point>
      <point>
        <x>70.1790005310</x>
        <y>0.0000957464</y>
      </point>
      <point>
        <x>68.1740032762</x>
        <y>0.0010930095</y>
      </point>
      <point>
        <x>66.1689987182</x>
        <y>0.0019999999</y>
      </point>
      <point>
        <x>64.1630015603</x>
        <y>0.0019121898</y>
      </point>
      <point>
        <x>62.1580009884</x>
        <y>0.0009147195</y>
      </point>
      <point>
        <x>60.1530002899</x>
        <y>-0.0000823168</y>
      </point>
      <point>
        <x>58.1479999625</x>
        <y>-0.0011591248</y>
      </point>
      <point>
        <x>56.1430054353</x>
        <y>-0.0031531883</y>
      </point>
      <point>
        <x>54.1380056104</x>
        <y>-0.0051477556</y>
      </point>
      <point>
        <x>52.1330065238</x>
        <y>-0.0071427085</y>
      </point>
      <point>
        <x>50.1280081832</x>
        <y>-0.0091367719</y>
      </point>
      <point>
        <x>48.1230121690</x>
        <y>-0.0111312658</y>
      </point>
      <point>
        <x>46.1170213739</x>
        <y>-0.0131894700</y>
      </point>
      <point>
        <x>44.1120148061</x>
        <y>-0.0161208523</y>
      </point>
      <point>
        <x>42.1070172065</x>
        <y>-0.0181153753</y>
      </point>
      <point>
        <x>40.1020312719</x>
        <y>-0.0201647967</y>
      </point>
      <point>
        <x>38.0970238475</x>
        <y>-0.0231039289</y>
      </point>
      <point>
        <x>36.0920240275</x>
        <y>-0.0250984835</y>
      </point>
      <point>
        <x>34.0870287457</x>
        <y>-0.0270934572</y>
      </point>
      <point>
        <x>32.0820155495</x>
        <y>-0.0290437619</y>
      </point>
      <point>
        <x>30.0770295817</x>
        <y>-0.0300820193</y>
      </point>
      <point>
        <x>28.0720168099</x>
        <y>-0.0320380413</y>
      </point>
      <point>
        <x>26.0659999847</x>
        <y>-0.0329999999</y>
      </point>
      <point>
        <x>24.0610176253</x>
        <y>-0.0330330670</y>
      </point>
      <point>
        <x>22.0559828639</x>
        <y>-0.0339696583</y>
      </point>
      <point>
        <x>20.0510005950</x>
        <y>-0.0329999999</y>
      </point>
      <point>
        <x>18.0459827543</x>
        <y>-0.0329753706</y>
      </point>
      <point>
        <x>16.0409693190</x>
        <y>-0.0319561997</y>
      </point>
      <point>
        <x>14.0359697043</x>
        <y>-0.0299616705</y>
      </point>
      <point>
        <x>12.0309584405</x>
        <y>-0.0279507087</y>
      </point>
      <point>
        <x>10.0259489067</x>
        <y>-0.0249461779</y>
      </point>
      <point>
        <x>8.0199587766</x>
        <y>-0.0209551641</y>
      </point>
      <point>
        <x>6.0149576802</x>
        <y>-0.0169588499</y>
      </point>
      <point>
        <x>4.0099704642</x>
        <y>-0.0119713338</y>
      </point>
      <point>
        <x>2.0034849198</x>
        <y>-0.0069748512</y>
      </point>
      <point>
        <x>0.0052212196</x>
        <y>-0.0000181743</y>
      </point>
      <lineMarking>no_marking</lineMarking>
    </leftBound>
    <rightBound>
      <point>
        <x>80.9080050048</x>
        <y>-192.3289949951</y>
      </point>
      <point>
        <x>82.3260042724</x>
        <y>-190.9109957275</y>
      </point>
      <point>
        <x>83.7427508053</x>
        <y>-189.4952426903</y>
      </point>
      <point>
        <x>85.1614995422</x>
        <y>-188.0765004577</y>
      </point>
      <point>
        <x>86.5794988098</x>
        <y>-186.6585011901</y>
      </point>
      <point>
        <x>87.9974980773</x>
        <y>-185.2405019226</y>
      </point>
      <point>
        <x>89.4157515705</x>
        <y>-183.8212647900</y>
      </point>
      <point>
        <x>90.8329966125</x>
        <y>-182.4040033874</y>
      </point>
      <point>
        <x>92.2497423346</x>
        <y>-180.9882342774</y>
      </point>
      <point>
        <x>93.6684995117</x>
        <y>-179.5695004882</y>
      </point>
      <point>
        <x>95.0864987792</x>
        <y>-178.1515012207</y>
      </point>
      <point>
        <x>96.5045018615</x>
        <y>-176.7334981384</y>
      </point>
      <point>
        <x>97.9227637981</x>
        <y>-175.3142694433</y>
      </point>
      <point>
        <x>99.3400003967</x>
        <y>-173.8969996032</y>
      </point>
      <point>
        <x>100.7570040283</x>
        <y>-172.4799959716</y>
      </point>
      <point>
        <x>102.1750032958</x>
        <y>-171.0619967041</y>
      </point>
      <point>
        <x>103.5930025634</x>
        <y>-169.6439974365</y>
      </point>
      <point>
        <x>105.0110018310</x>
        <y>-168.2259981689</y>
      </point>
      <point>
        <x>106.4287296676</x>
        <y>-166.8092188423</y>
      </point>
      <point>
        <x>107.8467234455</x>
        <y>-165.3922222108</y>
      </point>
      <point>
        <x>109.2655438835</x>
        <y>-163.9715679476</y>
      </point>
      <point>
        <x>110.6819956359</x>
        <y>-162.5550043640</y>
      </point>
      <point>
        <x>112.0997173029</x>
        <y>-161.1382199103</y>
      </point>
      <point>
        <x>113.5184979858</x>
        <y>-159.7195020141</y>
      </point>
      <point>
        <x>114.9365639286</x>
        <y>-158.2995703937</y>
      </point>
      <point>
        <x>116.3530044250</x>
        <y>-156.8829955749</y>
      </point>
      <point>
        <x>117.7707204679</x>
        <y>-155.4662054957</y>
      </point>
      <point>
        <x>119.1889994201</x>
        <y>-154.0480005798</y>
      </point>
      <point>
        <x>120.6067126496</x>
        <y>-152.6312076827</y>
      </point>
      <point>
        <x>122.0254979553</x>
        <y>-151.2125020446</y>
      </point>
      <point>
        <x>123.4430013122</x>
        <y>-149.7949986877</y>
      </point>
      <point>
        <x>124.8607103215</x>
        <y>-148.3782015703</y>
      </point>
      <point>
        <x>126.2794998474</x>
        <y>-146.9595001525</y>
      </point>
      <point>
        <x>127.6969955749</x>
        <y>-145.5420044250</y>
      </point>
      <point>
        <x>129.1147041814</x>
        <y>-144.1251992673</y>
      </point>
      <point>
        <x>130.5335841252</x>
        <y>-142.7046120969</y>
      </point>
      <point>
        <x>131.9505938319</x>
        <y>-141.2856080064</y>
      </point>
      <point>
        <x>133.3664970092</x>
        <y>-139.8695029907</y>
      </point>
      <point>
        <x>134.7854012874</x>
        <y>-138.4479168788</y>
      </point>
      <point>
        <x>136.2015965451</x>
        <y>-137.0296221789</y>
      </point>
      <point>
        <x>137.6176918941</x>
        <y>-135.6141946683</y>
      </point>
      <point>
        <x>139.0356940585</x>
        <y>-134.1971890714</y>
      </point>
      <point>
        <x>140.4538853606</x>
        <y>-132.7808741409</y>
      </point>
      <point>
        <x>141.8719544550</x>
        <y>-131.3674238962</y>
      </point>
      <point>
        <x>143.2921409465</x>
        <y>-129.9530933310</y>
      </point>
      <point>
        <x>144.7123133456</x>
        <y>-128.5397695971</y>
      </point>
      <point>
        <x>146.1350669185</x>
        <y>-127.1205389850</y>
      </point>
      <point>
        <x>147.5540590834</x>
        <y>-125.7045365466</y>
      </point>
      <point>
        <x>148.9754408527</x>
        <y>-124.2809617370</y>
      </point>
      <point>
        <x>150.3930096857</x>
        <y>-122.8560678336</y>
      </point>
      <point>
        <x>151.8094965678</x>
        <y>-121.4246364271</y>
      </point>
      <point>
        <x>153.2309777976</x>
        <y>-119.9514552556</y>
      </point>
      <point>
        <x>154.6417887253</x>
        <y>-118.4055216870</y>
      </point>
      <point>
        <x>156.0037959638</x>
        <y>-116.8240293042</y>
      </point>
      <point>
        <x>157.3706613917</x>
        <y>-115.1382775295</y>
      </point>
      <point>
        <x>158.6366899422</x>
        <y>-113.4787871790</y>
      </point>
      <point>
        <x>159.8548274345</x>
        <y>-111.7846335613</y>
      </point>
      <point>
        <x>161.0263160750</x>
        <y>-110.0537766338</y>
      </point>
      <point>
        <x>162.1448813340</x>
        <y>-108.2931355478</y>
      </point>
      <point>
        <x>163.2148326919</x>
        <y>-106.4999049564</y>
      </point>
      <point>
        <x>164.2322477306</x>
        <y>-104.6772979640</y>
      </point>
      <point>
        <x>165.1975091729</x>
        <y>-102.8255586363</y>
      </point>
      <point>
        <x>166.1089460002</x>
        <y>-100.9479864492</y>
      </point>
      <point>
        <x>166.9666067703</x>
        <y>-99.0444462154</y>
      </point>
      <point>
        <x>167.7694767151</x>
        <y>-97.1173357955</y>
      </point>
      <point>
        <x>168.5169949651</x>
        <y>-95.1687579635</y>
      </point>
      <point>
        <x>169.2090196830</x>
        <y>-93.1984671114</y>
      </point>
      <point>
        <x>169.8441620319</x>
        <y>-91.2109836669</y>
      </point>
      <point>
        <x>170.4225642376</x>
        <y>-89.2044745650</y>
      </point>
      <point>
        <x>170.9427473681</x>
        <y>-87.1821657409</y>
      </point>
      <point>
        <x>171.4051500801</x>
        <y>-85.1473711091</y>
      </point>
      <point>
        <x>171.8099100079</x>
        <y>-83.1000264092</y>
      </point>
      <point>
        <x>172.1555754661</x>
        <y>-81.0385921653</y>
      </point>
      <point>
        <x>172.4417933091</x>
        <y>-78.9722142805</y>
      </point>
      <point>
        <x>172.6693119260</x>
        <y>-76.8974596516</y>
      </point>
      <point>
        <x>172.8376829813</x>
        <y>-74.8165698848</y>
      </point>
      <point>
        <x>172.9459974364</x>
        <y>-72.7311369546</y>
      </point>
      <point>
        <x>172.9957500945</x>
        <y>-70.6456085659</y>
      </point>
      <point>
        <x>172.9855370886</x>
        <y>-68.5571105788</y>
      </point>
      <point>
        <x>172.9098638300</x>
        <y>-66.3875336545</y>
      </point>
      <point>
        <x>172.7757646304</x>
        <y>-64.3045919710</y>
      </point>
      <point>
        <x>172.5825358454</x>
        <y>-62.2266131206</y>
      </point>
      <point>
        <x>172.3298840401</x>
        <y>-60.1535667443</y>
      </point>
      <point>
        <x>172.0179343488</x>
        <y>-58.0889070872</y>
      </point>
      <point>
        <x>171.6468866755</x>
        <y>-56.0341840939</y>
      </point>
      <point>
        <x>171.2175237562</x>
        <y>-53.9923510781</y>
      </point>
      <point>
        <x>170.7304480255</x>
        <y>-51.9621121453</y>
      </point>
      <point>
        <x>170.1852545792</x>
        <y>-49.9466730704</y>
      </point>
      <point>
        <x>169.5831856568</x>
        <y>-47.9493206082</y>
      </point>
      <point>
        <x>168.9238220553</x>
        <y>-45.9672589172</y>
      </point>
      <point>
        <x>168.2084803513</x>
        <y>-44.0064158498</y>
      </point>
      <point>
        <x>167.4375999538</x>
        <y>-42.0667413710</y>
      </point>
      <point>
        <x>166.6107521644</x>
        <y>-40.1490024042</y>
      </point>
      <point>
        <x>165.7309514419</x>
        <y>-38.2578608785</y>
      </point>
      <point>
        <x>164.7954366101</x>
        <y>-36.3890919207</y>
      </point>
      <point>
        <x>163.8086438623</x>
        <y>-34.5511429157</y>
      </point>
      <point>
        <x>162.7688630825</x>
        <y>-32.7401411849</y>
      </point>
      <point>
        <x>161.6777274595</x>
        <y>-30.9599042686</y>
      </point>
      <point>
        <x>160.5364484289</x>
        <y>-29.2121423208</y>
      </point>
      <point>
        <x>159.3466244627</x>
        <y>-27.4983666734</y>
      </point>
      <point>
        <x>158.1067100015</x>
        <y>-25.8173964413</y>
      </point>
      <point>
        <x>156.8195859998</x>
        <y>-24.1733777750</y>
      </point>
      <point>
        <x>155.4874173956</x>
        <y>-22.5676784009</y>
      </point>
      <point>
        <x>154.1105442968</x>
        <y>-20.9999780449</y>
      </point>
      <point>
        <x>152.6280416511</x>
        <y>-19.4113021265</y>
      </point>
      <point>
        <x>151.1595377931</x>
        <y>-17.9289932087</y>
      </point>
      <point>
        <x>149.6498373249</x>
        <y>-16.4883898275</y>
      </point>
      <point>
        <x>148.0986786175</x>
        <y>-15.0904201098</y>
      </point>
      <point>
        <x>146.5081885944</x>
        <y>-13.7372755526</y>
      </point>
      <point>
        <x>144.8795193479</x>
        <y>-12.4307634369</y>
      </point>
      <point>
        <x>143.2147988672</x>
        <y>-11.1718345597</y>
      </point>
      <point>
        <x>141.5141284312</x>
        <y>-9.9603732777</y>
      </point>
      <point>
        <x>139.7801617387</x>
        <y>-8.7986535384</y>
      </point>
      <point>
        <x>138.0141901859</x>
        <y>-7.6864896359</y>
      </point>
      <point>
        <x>136.2166996856</x>
        <y>-6.6248715603</y>
      </point>
      <point>
        <x>134.3893514586</x>
        <y>-5.6150412223</y>
      </point>
      <point>
        <x>132.5333441303</x>
        <y>-4.6579124601</y>
      </point>
      <point>
        <x>130.6514459163</x>
        <y>-3.7545949809</y>
      </point>
      <point>
        <x>128.7461848100</x>
        <y>-2.9054361369</y>
      </point>
      <point>
        <x>126.8151955939</x>
        <y>-2.1098253305</y>
      </point>
      <point>
        <x>124.8627348386</x>
        <y>-1.3701590271</y>
      </point>
      <point>
        <x>122.8893184157</x>
        <y>-0.6868897093</y>
      </point>
      <point>
        <x>120.8973226575</x>
        <y>-0.0607453978</y>
      </point>
      <point>
        <x>118.8910829628</x>
        <y>0.5083708023</y>
      </point>
      <point>
        <x>116.8663505322</x>
        <y>1.0205854551</y>
      </point>
      <point>
        <x>114.8283840363</x>
        <y>1.4745526801</y>
      </point>
      <point>
        <x>112.7789639088</x>
        <y>1.8702694645</y>
      </point>
      <point>
        <x>110.7183833837</x>
        <y>2.2071461380</y>
      </point>
      <point>
        <x>108.6492126137</x>
        <y>2.4846289280</y>
      </point>
      <point>
        <x>106.4926871162</x>
        <y>2.7094005905</y>
      </point>
      <point>
        <x>104.4106753327</x>
        <y>2.8652635169</y>
      </point>
      <point>
        <x>102.3181625517</x>
        <y>2.9614983385</y>
      </point>
      <point>
        <x>100.2728963714</x>
        <y>2.9975938555</y>
      </point>
      <point>
        <x>98.2589501911</x>
        <y>3.0088057179</y>
      </point>
      <point>
        <x>96.2464946088</x>
        <y>3.0141350101</y>
      </point>
      <point>
        <x>94.2370130564</x>
        <y>3.0147313562</y>
      </point>
      <point>
        <x>92.2305258179</x>
        <y>3.0126024751</y>
      </point>
      <point>
        <x>90.2240352237</x>
        <y>3.0094789362</y>
      </point>
      <point>
        <x>88.2175386037</x>
        <y>3.0053598672</y>
      </point>
      <point>
        <x>86.2155263882</x>
        <y>3.0006293282</y>
      </point>
      <point>
        <x>84.2120115018</x>
        <y>2.9977602104</y>
      </point>
      <point>
        <x>82.2075078968</x>
        <y>2.9958828980</y>
      </point>
      <point>
        <x>80.2054937342</x>
        <y>2.9951126336</y>
      </point>
      <point>
        <x>78.2004893472</x>
        <y>2.9961096522</y>
      </point>
      <point>
        <x>76.1954920923</x>
        <y>2.9971066672</y>
      </point>
      <point>
        <x>74.1919882703</x>
        <y>2.9982059818</y>
      </point>
      <point>
        <x>72.1839981079</x>
        <y>3.0</y>
      </point>
      <point>
        <x>70.1804926984</x>
        <y>3.0000982134</y>
      </point>
      <point>
        <x>68.1754954435</x>
        <y>3.0010952285</y>
      </point>
      <point>
        <x>66.1689987182</x>
        <y>3.002</y>
      </point>
      <point>
        <x>64.1615090247</x>
        <y>3.0019087109</y>
      </point>
      <point>
        <x>62.1565091950</x>
        <y>3.0009112427</y>
      </point>
      <point>
        <x>60.1515081254</x>
        <y>2.9999142258</y>
      </point>
      <point>
        <x>58.1450163802</x>
        <y>2.9988329352</y>
      </point>
      <point>
        <x>56.1400211099</x>
        <y>2.9968389071</y>
      </point>
      <point>
        <x>54.1350205432</x>
        <y>2.9948447965</y>
      </point>
      <point>
        <x>52.1300229409</x>
        <y>2.9928498487</y>
      </point>
      <point>
        <x>50.1250238559</x>
        <y>2.9908558168</y>
      </point>
      <point>
        <x>48.1200285856</x>
        <y>2.9888617887</y>
      </point>
      <point>
        <x>46.1125448892</x>
        <y>2.9867979287</y>
      </point>
      <point>
        <x>44.1090304841</x>
        <y>2.9838726671</y>
      </point>
      <point>
        <x>42.1040328765</x>
        <y>2.9818777054</y>
      </point>
      <point>
        <x>40.0975559042</x>
        <y>2.9798233056</y>
      </point>
      <point>
        <x>38.0940395157</x>
        <y>2.9768896464</y>
      </point>
      <point>
        <x>36.0890389588</x>
        <y>2.9748955611</y>
      </point>
      <point>
        <x>34.0840451614</x>
        <y>2.9729005919</y>
      </point>
      <point>
        <x>32.0805233808</x>
        <y>2.9709540146</y>
      </point>
      <point>
        <x>30.0740459969</x>
        <y>2.9699125270</y>
      </point>
      <point>
        <x>28.0705246407</x>
        <y>2.9679599824</y>
      </point>
      <point>
        <x>26.0659999847</x>
        <y>2.967</y>
      </point>
      <point>
        <x>24.0595254560</x>
        <y>2.9669649554</y>
      </point>
      <point>
        <x>22.0574746591</x>
        <y>2.9660305944</y>
      </point>
      <point>
        <x>20.0510005950</x>
        <y>2.967</y>
      </point>
      <point>
        <x>18.0474749246</x>
        <y>2.9670246270</y>
      </point>
      <point>
        <x>16.0439536416</x>
        <y>2.9680418371</y>
      </point>
      <point>
        <x>14.0389540427</x>
        <y>2.9700368433</y>
      </point>
      <point>
        <x>12.0354338182</x>
        <y>2.9720441066</y>
      </point>
      <point>
        <x>10.0319175642</x>
        <y>2.9750439232</y>
      </point>
      <point>
        <x>8.0259259355</x>
        <y>2.9790339613</y>
      </point>
      <point>
        <x>6.0224203237</x>
        <y>2.9830238300</y>
      </point>
      <point>
        <x>4.0174293968</x>
        <y>2.9880113640</y>
      </point>
      <point>
        <x>2.0124416768</x>
        <y>2.9929964155</y>
      </point>
      <point>
        <x>0.0104424393</x>
        <y>2.9999636513</y>
      </point>
      <lineMarking>no_marking</lineMarking>
    </rightBound>
    <adjacentLeft ref="1" drivingDir="opposite"/>
    <laneletType>highway</laneletType>
  </lanelet>
  <planningProblem id="3">
    <initialState>
      <time>
        <exact>0</exact>
      </time>
      <position>
        <point>
          <x>10.0025781529</x>
          <y>-1.5249006637</y>
        </point>
      </position>
      <orientation>
        <exact>-0.0019897893</exact>
      </orientation>
      <velocity>
        <exact>0.0</exact>
      </velocity>
      <acceleration>
        <exact>0.0</exact>
      </acceleration>
      <yawRate>
        <exact>0.0</exact>
      </yawRate>
      <slipAngle>
        <exact>0.0</exact>
      </slipAngle>
    </initialState>
    <goalState>
      <time>
        <intervalStart>0</intervalStart>
        <intervalEnd>1000</intervalEnd>
      </time>
      <position>
        <rectangle>
          <length>10</length>
          <width>3</width>
          <orientation>0.7857418351169296</orientation>
          <center>
            <x>86.2146516878</x>
            <y>-180.6586271177</y>
          </center>
        </rectangle>
      </position>
    </goalState>
  </planningProblem>
</commonRoad>
